cpop/__init__.pyx
cpop/contract.pyx
cpop/data.pyx
cpop/dirs.pyx
cpop/exc.pyx
cpop/hub.pyx
cpop/loader.pyx
cpop/ref.pyx
cpop/scanner.pyx
cpop/verify.pyx
pop/config.yaml
pop/log/basic.py
pop/log/init.py
pop/log/timed_rolling.py
pop/log/contracts/init.py
pop/mods/config.py
pop/mods/contract.py
pop/mods/dyne.py
pop/mods/sub.py
pop/mods/task.py
pop/mods/test.py
cpop/__init__.cpython-312-x86_64-linux-gnu.so
cpop/contract.cpython-312-x86_64-linux-gnu.so
cpop/data.cpython-312-x86_64-linux-gnu.so
cpop/dirs.cpython-312-x86_64-linux-gnu.so
cpop/exc.cpython-312-x86_64-linux-gnu.so
cpop/hub.cpython-312-x86_64-linux-gnu.so
cpop/loader.cpython-312-x86_64-linux-gnu.so
cpop/ref.cpython-312-x86_64-linux-gnu.so
cpop/scanner.cpython-312-x86_64-linux-gnu.so
cpop/verify.cpython-312-x86_64-linux-gnu.so
cpop-36.0.2.dist-info/METADATA
cpop-36.0.2.dist-info/WHEEL
cpop-36.0.2.dist-info/RECORD
