Metadata-Version: 2.1
Name: cpop
Version: 36.0.2
Summary: The Cython-Optimized Plugin Oriented Programming System
Author-email: Tyler Levy Conde <yonstib@gmail.com>, Thomas Hatch <thatch45@gmail.com>
Classifier: Development Status :: 5 - Production/Stable
Classifier: License :: OSI Approved :: Apache Software License
Classifier: Operating System :: OS Independent
Classifier: Programming Language :: Python :: 3.10
Classifier: Programming Language :: Python :: 3.11
Classifier: Programming Language :: Python :: 3.12
Requires-Python: >=3.10
Requires-Dist: aiofiles
Requires-Dist: aiologger
Requires-Dist: aiopath
Requires-Dist: argparse
Requires-Dist: msgpack
Requires-Dist: pyyaml
Provides-Extra: build
Requires-Dist: cython; extra == 'build'
Requires-Dist: hatch; extra == 'build'
Requires-Dist: hatch-cython; extra == 'build'
Provides-Extra: cli
Requires-Dist: pop-cli; extra == 'cli'
Provides-Extra: test
Requires-Dist: pytest; extra == 'test'
Requires-Dist: pytest-asyncio; extra == 'test'
